verilog/modules/cache.v
module cache (
    c_busywait_o, c_data_o, reset_i, clk_i, address_i
);
    parameter c_line_size = 32, c_assiotivity = 1, c_index = 4, c_block_size = 2; // cache line size, assiotivity, index size, block size
    parameter c_tag_size = c_line_size - c_index - c_block_size - 2;
    integer i, j;

    input reset_i, clk_i;
    input [c_line_size - 1:0] address_i;

    output reg [c_line_size - 1:0] c_data_o;
    output reg c_busywait_o;


    reg [c_line_size - 1 : 0] c_word[0 : (2**c_index) - 1][0 : (2**c_assiotivity) - 1][0 : (2**c_block_size) - 1]; //cache word
    reg [c_tag_size - 1 : 0] c_tag[0 : (2**c_index) - 1][0 : (2**c_assiotivity) - 1];  //cache tag
    reg c_valid_bit [0 : (2**c_index) - 1][0 : (2**c_assiotivity) - 1]; //cache valid bit

    wire [c_block_size - 1:0] offset_addr;
    wire [c_index - 1:0] index_addr;
    wire [c_tag_size - 1:0] tag_addr;


    reg valid_bit_frm_c [0 : (2**c_assiotivity) - 1], hit_frm_c [0 : (2**c_assiotivity) - 1], hit_frm_c_AND_valid_bit_frm_c [0 : (2**c_assiotivity) - 1];
    reg [c_tag_size - 1:0] tag_frm_c [0 : (2**c_assiotivity) - 1];
    reg [c_line_size - 1 : 0] data_frm_c [0 : (2**c_assiotivity) - 1];

    reg [c_assiotivity - 1 : 0] hit_cache_assiotivity;
    reg c_hit;


    //{tag_addr:}{index_addr:}{offset_addr:}{2}
    assign offset_addr = address_i[c_block_size + 1:2];
    assign index_addr = address_i[c_index + c_block_size + 1:c_block_size + 2];
    assign tag_addr = address_i[c_line_size - 1:c_index + c_block_size + 2];


    always @(*) begin
        c_hit = 1'b0;
        for (i = 0; i < c_assiotivity; i = i + 1) begin
            valid_bit_frm_c[i] = c_valid_bit[index_addr][i];
            tag_frm_c[i] = c_tag[index_addr][i];
            hit_frm_c[i] = (tag_addr === tag_frm_c[i]) ? 1'b1 : 1'b0;
            hit_frm_c_AND_valid_bit_frm_c[i] = valid_bit_frm_c[i] && hit_frm_c[i];
            data_frm_c[i] = c_word[index_addr][i][offset_addr];

            if (hit_frm_c_AND_valid_bit_frm_c[i]) begin
                c_hit = 1'b1;
                c_data_o = data_frm_c[i]; 
            end
            // else
            // begin
            //     hit = 1'b0;
            // end

        end
    end

    //busy wait
    always @(posedge clk_i) begin
        if (!c_hit) 
            c_busywait_o = 1'b1;
        else
            c_busywait_o = 1'b0;
    end

    

    always @(posedge clk_i, reset_i)
    begin
        if(reset_i)
        begin
            for (i = 0; i < 2**c_index; i = i + 1) begin
                for (j = 0; j < 2**c_assiotivity; j = j + 1) begin
                    c_valid_bit[i][j] = 0;
                end
            end
        end
        else
        begin
            //need to integreate
            for (i = 0; i < 2**c_index; i = i + 1) begin
                for (j = 0; j < 2**c_assiotivity; j = j + 1) begin
                    c_valid_bit[9][0] = 0;
                    c_tag[9][0] = 24'h800001;
                    c_word[9][0][2] = 32'b11;
                end
            end
        end
    end
    

endmodule

verilog/testbench/cache.v
`timescale 1ns/1ps

`include "../modules/cache.v"


module testcache;

    // input reset, clk;
    // input [line_size - 1:0] address;

    // output reg [line_size - 1:0] data;
    // output busywait;
    parameter line_size = 32;

    wire busywait;
    wire [line_size - 1:0] data;
    reg [line_size - 1:0] address;
    reg clk,reset;
    integer i,j;
    

    cache mycache(busywait, data, reset, clk, address);

	//wavedata file
	initial
	begin
		$dumpfile("wavedata.vcd");
		$dumpvars(0,testcache);
        // $dumpvars(0, mycache.tag_reg[0]);
    
        // for(i = 0; i < 4; i = i + 1)begin
        //     // $dumpvars(0, mycache.c_valid_bit[1][i]);
        //     $dumpvars(0, mycache.c_valid_bit[9][i]);
        // end
        $dumpvars(0, mycache.c_valid_bit[9][0]);
        $dumpvars(0, mycache.c_valid_bit[9][1]);

        $dumpvars(0, mycache.c_tag[9][0]);
        $dumpvars(0, mycache.c_tag[9][1]);

        $dumpvars(0, mycache.c_word[9][0][2]);
        $dumpvars(0, mycache.c_word[9][1][2]);
        $dumpvars(0, mycache.c_word[9][0][3]);
        $dumpvars(0, mycache.c_word[9][1][3]);

        // $dumpvars(0, mycache.c_valid_bit[9][0]);
        // $dumpvars(0, mycache.c_valid_bit[9][1]);

        for(i = 0; i < 2; i = i + 1)begin
            // $dumpvars(0, mycache.c_valid_bit[1][i]);
            $dumpvars(0, mycache.valid_bit_frm_c[i]);
            $dumpvars(0, mycache.tag_frm_c[i]);
            $dumpvars(0, mycache.hit_frm_c[i]);
            $dumpvars(0, mycache.hit_frm_c_AND_valid_bit_frm_c[i]);
            $dumpvars(0, mycache.data_frm_c[i]);
        end
        
	end

  //clock 
	always 
	begin
			#5	clk = ~clk;
	end

	//running
	initial
	begin
        clk = 1'b1;
        #1
        reset <= 1'b1;

        #1
        reset <= 1'b0;

        #5 
        address <= 32'b100000000000000000000001_1001_10_10;
        
        #10
        address <= 32'd2;

        #10
        reset <= 1'b1;

        #10

        $finish;

	end
		 
endmodule

verilog/testbench/wavedata.vcd
$date
	Fri Jan 12 16:41:48 2024
$end
$version
	Icarus Verilog
$end
$timescale
	1ps
$end
$scope module testcache $end
$var wire 32 ! data [31:0] $end
$var wire 1 " busywait $end
$var parameter 32 # line_size $end
$var reg 32 $ address [31:0] $end
$var reg 1 % clk $end
$var reg 1 & reset $end
$var integer 32 ' i [31:0] $end
$scope module mycache $end
$var wire 32 ( address_i [31:0] $end
$var wire 1 % clk_i $end
$var wire 1 & reset_i $end
$var wire 24 ) tag_addr [23:0] $end
$var wire 2 * offset_addr [1:0] $end
$var wire 4 + index_addr [3:0] $end
$var parameter 32 , c_assiotivity $end
$var parameter 32 - c_block_size $end
$var parameter 32 . c_index $end
$var parameter 32 / c_line_size $end
$var parameter 35 0 c_tag_size $end
$var reg 1 " c_busywait_o $end
$var reg 32 1 c_data_o [31:0] $end
$var reg 1 2 c_hit $end
$var integer 32 3 i [31:0] $end
$var integer 32 4 j [31:0] $end
$upscope $end
$upscope $end
$scope module testcache $end
$scope module mycache $end
$var reg 1 5 \c_valid_bit[18] $end
$upscope $end
$upscope $end
$scope module testcache $end
$scope module mycache $end
$var reg 1 6 \c_valid_bit[19] $end
$upscope $end
$upscope $end
$scope module testcache $end
$scope module mycache $end
$var reg 24 7 \c_tag[18] [23:0] $end
$upscope $end
$upscope $end
$scope module testcache $end
$scope module mycache $end
$var reg 24 8 \c_tag[19] [23:0] $end
$upscope $end
$upscope $end
$scope module testcache $end
$scope module mycache $end
$var reg 32 9 \c_word[74] [31:0] $end
$upscope $end
$upscope $end
$scope module testcache $end
$scope module mycache $end
$var reg 32 : \c_word[78] [31:0] $end
$upscope $end
$upscope $end
$scope module testcache $end
$scope module mycache $end
$var reg 32 ; \c_word[75] [31:0] $end
$upscope $end
$upscope $end
$scope module testcache $end
$scope module mycache $end
$var reg 32 < \c_word[79] [31:0] $end
$upscope $end
$upscope $end
$scope module testcache $end
$scope module mycache $end
$var reg 1 = \valid_bit_frm_c[0] $end
$upscope $end
$upscope $end
$scope module testcache $end
$scope module mycache $end
$var reg 24 > \tag_frm_c[0] [23:0] $end
$upscope $end
$upscope $end
$scope module testcache $end
$scope module mycache $end
$var reg 1 ? \hit_frm_c[0] $end
$upscope $end
$upscope $end
$scope module testcache $end
$scope module mycache $end
$var reg 1 @ \hit_frm_c_AND_valid_bit_frm_c[0] $end
$upscope $end
$upscope $end
$scope module testcache $end
$scope module mycache $end
$var reg 32 A \data_frm_c[0] [31:0] $end
$upscope $end
$upscope $end
$scope module testcache $end
$scope module mycache $end
$var reg 1 B \valid_bit_frm_c[1] $end
$upscope $end
$upscope $end
$scope module testcache $end
$scope module mycache $end
$var reg 24 C \tag_frm_c[1] [23:0] $end
$upscope $end
$upscope $end
$scope module testcache $end
$scope module mycache $end
$var reg 1 D \hit_frm_c[1] $end
$upscope $end
$upscope $end
$scope module testcache $end
$scope module mycache $end
$var reg 1 E \hit_frm_c_AND_valid_bit_frm_c[1] $end
$upscope $end
$upscope $end
$scope module testcache $end
$scope module mycache $end
$var reg 32 F \data_frm_c[1] [31:0] $end
$upscope $end
$upscope $end
$enddefinitions $end
$comment Show the parameter values. $end
$dumpall
b11000 0
b100000 /
b100 .
b10 -
b1 ,
b100000 #
$end
#0
$dumpvars
bx F
xE
xD
bx C
xB
bx A
x@
1?
bx >
x=
bx <
bx ;
bx :
b11 9
bx 8
b100000000000000000000001 7
x6
05
b10 4
b1 3
02
bx 1
bx +
bx *
bx )
bx (
b10 '
x&
1%
bx $
0"
bx !
$end
#1000
bx A
x@
1?
bx >
x=
06
05
b10 4
b1 3
1&
#2000
b11 9
b100000000000000000000001 7
05
b10 4
b10000 3
0&
#5000
0%
#7000
b11 A
0@
1?
b100000000000000000000001 >
0=
b1 3
b10 *
b1001 +
b100000000000000000000001 )
b10000000000000000000000110011010 $
b10000000000000000000000110011010 (
#10000
b11 9
b100000000000000000000001 7
05
b10 4
b10000 3
1"
1%
#15000
0%
#17000
bx A
0@
0?
bx >
0=
b1 3
b0 *
b0 +
b0 )
b10 $
b10 (
#20000
b11 9
b100000000000000000000001 7
05
b10 4
b10000 3
1%
#25000
0%
#27000
06
05
b10 4
b10000 3
1&
#30000
06
05
b10 4
b10000 3
1%
