verilog/modules/memory.v
module memory #(parameter  c_block_size = 2, c_line_size = 64, address_size = 32, mem_line_size = 32) (
    m_busywait_o, m_read_data_o, m_write_done, m_read_done, m_clk_i, m_reset_i, m_read_i, m_wr_i, m_addr_i, m_wr_data_i
);

    

    input m_clk_i, m_read_i, m_wr_i, m_reset_i;
    input [address_size - c_block_size - 3:0] m_addr_i;
    input [2**c_block_size*c_line_size - 1 : 0] m_wr_data_i;

    output reg [2**c_block_size*c_line_size - 1 : 0] m_read_data_o;
    output reg m_busywait_o;
    output reg m_write_done, m_read_done;

    reg [c_block_size - 1:0] byte_read_count;

    reg [mem_line_size - 1:0] memory [0:2047];

    reg [2**c_block_size*c_line_size - 1 : 0] data_to_be_write;

    // assign data_to_be_write = m_wr_data_i[mem_line_size * byte_read_count - 1 : mem_line_size * (byte_read_count - 1)];


    // wire mem_access;

    // assign mem_access <= (m_read_i || m_wr_data_i);

    initial begin
        $readmemh("../modules/mem.data", memory);
    end

    // assign m_read_data_o = {memory[0], memory[1], memory[2], memory[3]};
    // assign m_busywait_o = 1'b0;

    // always @(*posedge m_clk_i) begin
    //     m_busywait_o <= mem_access ? 1'b1 : 1'b0;

    // end


    //
    // always @(posedge m_clk_i, m_busywait_o) begin
    //     if(m_busywait_o) byte_read_count = byte_read_count + 1;
    // end

    parameter IDLE = 3'b000, MEM_READ = 3'b001, MEM_WRITE = 3'b010, MEM_READ_DONE = 3'b011, MEM_WRITE_DONE = 3'b100;

    reg [2:0] m_state, m_n_state;
    //control signals based on state
    always @(*) begin
        case (m_state)
            IDLE: begin
                m_busywait_o = 1'b0;
                m_write_done = 1'b0;
                m_read_done = 1'b0;
            end
            MEM_READ: begin
                m_busywait_o = 1'b1;
                m_write_done = 1'b0;
                m_read_done = 1'b0;
                // m_read_data_o[mem_line_size * byte_read_count - 1 : mem_line_size * (byte_read_count - 1)] = memory[{m_addr_i, byte_read_count}];
                // m_read_data_o = {memory[{m_addr_i, byte_read_count}], };

            end
            MEM_WRITE: begin
                m_busywait_o = 1'b1;
                m_write_done = 1'b0;
                m_read_done = 1'b0;
                // memory[{m_addr_i, byte_read_count}] = m_wr_data_i[mem_line_size * byte_read_count - 1 : mem_line_size * (byte_read_count - 1)];
            end
            MEM_READ_DONE: begin
                m_busywait_o = 1'b0;
                m_write_done = 1'b0;
                m_read_done = 1'b1;
            end
            MEM_WRITE_DONE: begin
                m_busywait_o = 1'b0;
                m_write_done = 1'b1;
                m_read_done = 1'b0;
            end
        endcase
    end
    reg [mem_line_size - 1:0] tmp_read_data;
    // always @(*)begin
    //     tmp = {m_addr_i, byte_read_count};
    // end

    always @(posedge m_clk_i, posedge m_reset_i) begin
        if (m_reset_i) begin
            m_state = IDLE;
            // m_n_state = IDLE;
            tmp_read_data = 0;
        end
        else begin
            m_state <= m_n_state;
            m_read_data_o = m_read_data_o >> mem_line_size;
            m_read_data_o[2**c_block_size*c_line_size - 1 : 2**c_block_size*c_line_size - mem_line_size] = tmp_read_data;
        end
    end
    
    always @(posedge m_clk_i, posedge m_reset_i) begin
        if (m_reset_i) begin
            tmp_read_data = 0;
        end
        #1
        case (m_state)
            IDLE: begin
                data_to_be_write = m_wr_data_i;
                // tmp_read_data = 0;
            end
            MEM_READ: begin
                // m_read_data_o = m_read_data_o >> mem_line_size;
                tmp_read_data = memory[{m_addr_i, byte_read_count}];
                // m_read_data_o[2**c_block_size*c_line_size - 1 : 2**c_block_size*c_line_size - mem_line_size] = memory[{m_addr_i, byte_read_count}];
            end
            MEM_WRITE: begin
                memory[{m_addr_i, byte_read_count}] = data_to_be_write[mem_line_size - 1:0];
                data_to_be_write = data_to_be_write >> mem_line_size;
                //m_wr_data_i[mem_line_size * byte_read_count - 1 : mem_line_size * (byte_read_count - 1)];
                // m_wr_data_i = m_wr_data_i >> m_wr_data_i;                
            end
        endcase
    end

    //state transission
    always @(*) begin
        case (m_state)
            IDLE: begin
                if(m_read_i) m_n_state = MEM_READ;
                else if (m_wr_i) m_n_state = MEM_WRITE;
                else m_n_state = IDLE;
            end
            MEM_READ: begin
                if(&byte_read_count) m_n_state = MEM_READ_DONE;
            end
            MEM_WRITE: begin
                if(&byte_read_count) m_n_state = MEM_WRITE_DONE;
            end
            MEM_READ_DONE: begin
                m_n_state = IDLE;
            end
            MEM_WRITE_DONE: begin
                m_n_state = IDLE;
            end

        endcase
    end


    //counter
    always @(posedge m_clk_i) begin
        // #1
        case (m_state)
            IDLE: byte_read_count = 0;
            MEM_READ: byte_read_count = byte_read_count + 1;
            MEM_WRITE: byte_read_count = byte_read_count + 1;
            MEM_READ_DONE: byte_read_count = 0;
            MEM_WRITE_DONE: byte_read_count = 0;
        endcase
    end
    
endmodule

verilog/modules/cache.v
// `include "./memory.v"

module cache (
    c_busywait_o, c_data_o, c_m_write_data_o, c_m_read_o, c_m_wr_o, c_m_address_o, reset_i, clk_i, address_i, c_read_i, c_wr_i, c_write_data_i, c_m_busywait_i, c_m_read_data_i, m_write_done, m_read_done
);

    parameter c_line_size = 32, c_assiotivity = 2, c_index = 4, c_block_size = 2, address_size = 32; // cache line size, assiotivity, index size, block size
    parameter c_tag_size = c_line_size - c_index - c_block_size - 2;
    // parameter c_block_size = c_line_size*(2**c_block_size);
    integer i, j;

    input reset_i, clk_i, c_read_i, c_wr_i;
    input [address_size - 1:0] address_i;

    //for data memory from cache
    output reg c_m_read_o, c_m_wr_o;
    output reg [2**c_block_size*c_line_size - 1:0] c_m_write_data_o;
    output reg [address_size - c_block_size - 3:0] c_m_address_o;
    input [2**c_block_size*c_line_size - 1:0] c_m_read_data_i;
    input c_m_busywait_i, m_write_done, m_read_done;
    input [c_line_size - 1:0] c_write_data_i;


    output reg [c_line_size - 1:0] c_data_o;
    output reg c_busywait_o;


    reg [2**c_block_size*c_line_size - 1 : 0] c_word[0 : (2**c_index) - 1][0 : (2**c_assiotivity) - 1]; //cache word
    reg [c_tag_size - 1 : 0] c_tag[0 : (2**c_index) - 1][0 : (2**c_assiotivity) - 1];  //cache tag
    reg c_valid_bit [0 : (2**c_index) - 1][0 : (2**c_assiotivity) - 1]; //cache valid bit
    reg c_dirty_bit [0 : (2**c_index) - 1][0 : (2**c_assiotivity) - 1]; //cache dirty bit
    reg [2:0] c_usability_bit [0 : (2**c_index) - 1][0 : (2**c_assiotivity) - 1]; //cache dirty bit

    wire [c_block_size - 1:0] offset_addr;
    wire [c_index - 1:0] index_addr;
    wire [c_tag_size - 1:0] tag_addr;


    reg valid_bit_frm_c [0 : (2**c_assiotivity) - 1];
    reg hit_frm_c [0 : (2**c_assiotivity) - 1];
    reg hit_frm_c_AND_valid_bit_frm_c [0 : (2**c_assiotivity) - 1];
    reg dirty_bit_frm_c [0 : (2**c_assiotivity) - 1];
    reg [c_tag_size - 1 : 0] tag_frm_c [0 : (2**c_assiotivity) - 1];
    reg [c_line_size - 1 : 0] data_frm_c [0 : (2**c_assiotivity) - 1];
    reg [2:0] usability_bit_frm_c [0 : (2**c_assiotivity) - 1];

    // reg [c_assiotivity - 1 : 0] hit_cache_assiotivity;
    reg c_hit;

    reg [c_assiotivity - 1:0] c_hit_set_place;
    reg [2**c_block_size*c_line_size - 1:0] c_write_data_pre;
    reg [2**c_block_size*c_line_size - 1:0] c_write_data_pre_all_, c_block_data_with_mask, tmp;

    always @(*) begin
        c_block_data_with_mask = c_word[index_addr][c_hit_set_place] & ~({c_line_size{1'b1}} << (offset_addr * c_line_size));
        c_write_data_pre = c_write_data_pre_all_ ^ c_write_data_i << (offset_addr * c_line_size);
        tmp = c_block_data_with_mask | c_write_data_pre;
        
    end


    //{tag_addr:}{index_addr:}{offset_addr:}{2}
    assign offset_addr = address_i[c_block_size + 1:2];
    assign index_addr = address_i[c_index + c_block_size + 1:c_block_size + 2];
    assign tag_addr = address_i[c_line_size - 1:c_index + c_block_size + 2];

    // reg [c_block_size - 1:0] offset_addr_tmp;
    
    // always @(*) begin
    //     offset_addr_tmp = offset_addr;
        
    // end

    //
    wire [address_size - c_block_size - 3:0] c_m_address_read, c_m_address_wr;

    //address for data memeory
    assign c_m_address_read = {address_i[address_size : c_block_size + 2]};

    assign c_m_address_wr = tag_frm_c[less_used_assiotivity];

    //data for mem write
    // assign c_m_write_data_o = data_frm_c[less_used_assiotivity];


    //read data, valid bit, check tag == cache tag from cache sets
    // integer offset = offset_addr*c_line_size;
    // integer tmp;
    // always @(posedge clk) begin
    //     tmp = offset_addr*c_line_size;
    // end
    
    always @(*) begin
        c_hit = 1'b0;
        c_hit_set_place = 0;
        for (i = 0; i < 2**c_assiotivity; i = i + 1) begin
            valid_bit_frm_c[i] = c_valid_bit[index_addr][i];
            tag_frm_c[i] = c_tag[index_addr][i];
            dirty_bit_frm_c[i] = c_dirty_bit[index_addr][i];
            hit_frm_c[i] = (tag_addr === tag_frm_c[i]) ? 1'b1 : 1'b0;
            hit_frm_c_AND_valid_bit_frm_c[i] = valid_bit_frm_c[i] && hit_frm_c[i];
            data_frm_c[i] = c_word[index_addr][i] >> (offset_addr * c_line_size);
            usability_bit_frm_c[i] = c_usability_bit[index_addr][i];

            if (hit_frm_c_AND_valid_bit_frm_c[i]) begin
                c_hit = 1'b1;
                c_hit_set_place = i;
                c_data_o = data_frm_c[i];
            end
        end
    end

    //select less used cache assiotivity
    integer less_used_assiotivity;
    always @(*) begin
        less_used_assiotivity = 0;
        for (i = 1; i < 2**c_assiotivity; i = i + 1) begin
            if (usability_bit_frm_c[less_used_assiotivity] > usability_bit_frm_c[i]) less_used_assiotivity = i;
        end
    end

    //dirty bit wire
    wire is_dirty;
    assign is_dirty = dirty_bit_frm_c[less_used_assiotivity];

    // //busy wait
    // always @(*) begin
    //     if (!c_hit & (c_read_i | c_wr_i)) 
    //         c_busywait_o = 1'b1;
    //     else
    //         c_busywait_o = 1'b0;
    // end

    always @(posedge clk_i, reset_i)
    begin
        if(reset_i)
        begin
            for (i = 0; i < 2**c_index; i = i + 1) begin
                for (j = 0; j < 2**c_assiotivity; j = j + 1) begin
                    c_valid_bit[i][j] = 0;
                    c_word[i][j] = 0;
                    // c_word[i][j][1] = 0;
                    // c_word[i][j][2] = 0;
                    // c_word[i][j][3] = 0;
                    c_tag[i][j] = 0;
                    c_dirty_bit[i][j] = 0;
                    c_usability_bit[i][j] = 0;
                end
            end
        end
        else
        begin

            if(c_allow_wr) begin
                c_valid_bit[index_addr][less_used_assiotivity] = 1'b1;
                c_dirty_bit[i][j] = 0;
                c_tag[index_addr][less_used_assiotivity] = tag_addr;
                c_word[index_addr][less_used_assiotivity] = c_m_read_data_i;
                c_usability_bit[index_addr][less_used_assiotivity] = usability_bit_frm_c[less_used_assiotivity] + 1;

                for (i = 1; i < 2**c_assiotivity; i = i + 1) begin
                    if(i !== less_used_assiotivity)begin
                        if (c_usability_bit[index_addr][i] <= 1) begin
                            c_usability_bit[index_addr][i] = 0;
                        end
                        else c_usability_bit[index_addr][i] = c_usability_bit[index_addr][i] - 1;
                    end
                end

                // c_usability_bit[index_addr][less_used_assiotivity] = 3'd2;
                // c_usability_bit[index_addr][less_used_assiotivity] = 3'd1;
                // c_usability_bit[index_addr][less_used_assiotivity] = 3'd4;
                // for (i = 0; i < 2**c_block_size; i = i + 1) begin
                //     c_word[index_addr][less_used_assiotivity][i] = c_m_read_data_i[(i+1)*c_line_size : i*c_line_size];
                // end

            end
            else if (c_update_en) begin
                c_word[index_addr][c_hit_set_place] = c_block_data_with_mask | c_write_data_pre;
                c_usability_bit[index_addr][c_hit_set_place] = usability_bit_frm_c[c_hit_set_place] + 1;
                c_dirty_bit[index_addr][c_hit_set_place] = 1;

                // c_valid_bit[index_addr][less_used_assiotivity] = 1'b1;
                // c_tag[index_addr][less_used_assiotivity] = tag_addr;
                // c_word[index_addr][less_used_assiotivity] = c_m_read_data_i;
                // c_usability_bit[index_addr][less_used_assiotivity] = usability_bit_frm_c[less_used_assiotivity] + 1;
                // c_dirty_bit[index_addr][]

                for (i = 1; i < 2**c_assiotivity; i = i + 1) begin
                    if(i !== c_hit_set_place)begin
                        if (c_usability_bit[index_addr][i] <= 1) begin
                            c_usability_bit[index_addr][i] = 0;
                        end
                        else c_usability_bit[index_addr][i] = c_usability_bit[index_addr][i] - 1;
                    end
                end
            end
        end
    end
    
    //state machine
    parameter IDLE = 3'b000, MEM_READ = 3'b001, MEM_WRITE = 3'b010, MEM_READ_DONE = 3'b011, MEM_WRITE_DONE = 3'b100;   //, CACHE_WRITE_BACK = 3'b011;
    reg [2:0] c_state, c_n_state;
    reg c_allow_wr, c_update_en;

    //state transisstion
    always @(*)
    begin
        case (c_state)
            IDLE: begin
                if(!c_hit && (c_read_i || c_wr_i) && is_dirty) begin
                    c_n_state <= MEM_WRITE;
                end
                else if (!c_hit && (c_read_i || c_wr_i) && !is_dirty) begin
                    c_n_state <= MEM_READ;
                end
                else
                    c_n_state <= IDLE;
            end
            MEM_READ: begin
                if(!c_m_busywait_i && m_read_done) c_n_state = MEM_READ_DONE;
            end
            MEM_WRITE: begin
                if(!c_m_busywait_i && m_write_done) c_n_state = MEM_WRITE_DONE;
            end
            MEM_READ_DONE: begin
                c_n_state = IDLE;
            end
            MEM_WRITE_DONE: begin
                c_n_state = IDLE;
            end
        endcase
    end

    //combination logic for cache control signals
    always @(*)
    begin
        case (c_state)
            IDLE: begin
                c_busywait_o <= 1'b0;
                c_m_read_o <= 1'b0;
                c_m_wr_o <= 1'b0;
                c_allow_wr <= 1'b0;
                c_update_en <= c_wr_i ?  1'b1 : 1'b0;
                c_m_address_o = c_m_address_read;
            end
            MEM_READ: begin
                c_busywait_o <= 1'b1;
                c_m_read_o <= m_read_done ? 1'b0 : 1'b1;
                c_m_wr_o <= 1'b0;
                c_allow_wr <= m_read_done ? 1'b1 : 1'b0;
                c_update_en <= 1'b0;
                c_m_address_o = c_m_address_read;
            end
            MEM_WRITE: begin
                c_busywait_o <= 1'b1;
                c_m_read_o <= 1'b0;
                c_m_wr_o <= m_write_done ? 1'b0 : 1'b1;;
                c_allow_wr <= 1'b0;
                c_m_address_o = c_m_address_wr;
                c_update_en <= 1'b0;
                c_m_write_data_o = data_frm_c[less_used_assiotivity];
            end
            MEM_READ_DONE: begin
                c_busywait_o <= 1'b0;
                c_m_read_o <= 1'b0;
                c_m_wr_o <= 1'b0;
                c_allow_wr <= 1'b0;
                c_update_en <= 1'b0;
                c_m_address_o = c_m_address_read;
            end
            MEM_WRITE_DONE: begin
                c_busywait_o <= 1'b1;
                c_m_read_o <= 1'b0;
                c_m_wr_o <= 1'b0;
                c_allow_wr <= 1'b0;
                c_update_en <= 1'b0;
                c_m_address_o = c_m_address_read;
            end
        endcase
    end

    //cache state change
    always @(posedge clk_i, posedge reset_i) begin
        if (reset_i) begin
            c_state <= IDLE;
            c_write_data_pre_all_ = 0;

        end
        else begin
            c_state <= c_n_state;
            // c_write_data_pre_all_ = c_write_data_pre_all_;
        end
    end

endmodule

verilog/testbench/cache.v
`timescale 1ns/1ps

`include "../modules/cache.v"


module testcache;

    // input reset, clk;
    // input [line_size - 1:0] address;

    // output reg [line_size - 1:0] data;
    // output busywait;
    parameter line_size = 32;

    wire busywait;
    wire [line_size - 1:0] data;
    reg [line_size - 1:0] address;
    reg clk,reset,c_read_i,c_wr_i;
    integer i,j;
    

    cache mycache(busywait, data, reset, clk, address, c_read_i, c_wr_i);

	//wavedata file
	initial
	begin
		$dumpfile("wavedata.vcd");
		$dumpvars(0,testcache);
        // $dumpvars(0, mycache.tag_reg[0]);
    
        // for(i = 0; i < 4; i = i + 1)begin
        //     // $dumpvars(0, mycache.c_valid_bit[1][i]);
        //     $dumpvars(0, mycache.c_valid_bit[9][i]);
        // end
        $dumpvars(0, mycache.c_valid_bit[9][0]);
        $dumpvars(0, mycache.c_valid_bit[9][1]);

        $dumpvars(0, mycache.c_tag[9][0]);
        $dumpvars(0, mycache.c_tag[9][1]);

        $dumpvars(0, mycache.c_word[9][1][0]);
        $dumpvars(0, mycache.c_word[9][1][1]);
        $dumpvars(0, mycache.c_word[9][1][2]);
        $dumpvars(0, mycache.c_word[9][1][3]);

        $dumpvars(0, mycache.valid_bit_frm_c[0]);
        $dumpvars(0, mycache.valid_bit_frm_c[1]);
        $dumpvars(0, mycache.valid_bit_frm_c[2]);
        $dumpvars(0, mycache.valid_bit_frm_c[3]);

        $dumpvars(0, mycache.tag_frm_c[0]);
        $dumpvars(0, mycache.tag_frm_c[1]);
        $dumpvars(0, mycache.tag_frm_c[2]);
        $dumpvars(0, mycache.tag_frm_c[3]);

        $dumpvars(0, mycache.hit_frm_c[0]);
        $dumpvars(0, mycache.hit_frm_c[1]);
        $dumpvars(0, mycache.hit_frm_c[2]);
        $dumpvars(0, mycache.hit_frm_c[3]);

        $dumpvars(0, mycache.hit_frm_c_AND_valid_bit_frm_c[0]);
        $dumpvars(0, mycache.hit_frm_c_AND_valid_bit_frm_c[1]);
        $dumpvars(0, mycache.hit_frm_c_AND_valid_bit_frm_c[2]);
        $dumpvars(0, mycache.hit_frm_c_AND_valid_bit_frm_c[3]);

        $dumpvars(0, mycache.data_frm_c[0]);
        $dumpvars(0, mycache.data_frm_c[1]);
        $dumpvars(0, mycache.data_frm_c[2]);
        $dumpvars(0, mycache.data_frm_c[3]);

        $dumpvars(0, mycache.usability_bit_frm_c[0]);
        $dumpvars(0, mycache.usability_bit_frm_c[1]);
        $dumpvars(0, mycache.usability_bit_frm_c[2]);
        $dumpvars(0, mycache.usability_bit_frm_c[3]);

        // for(i = 0; i < 2; i = i + 1)begin
        //     // $dumpvars(0, mycache.c_valid_bit[1][i]);
        //     $dumpvars(0, mycache.valid_bit_frm_c[i]);
        //     $dumpvars(0, mycache.tag_frm_c[i]);
        //     $dumpvars(0, mycache.hit_frm_c[i]);
        //     $dumpvars(0, mycache.hit_frm_c_AND_valid_bit_frm_c[i]);
        //     $dumpvars(0, mycache.data_frm_c[i]);
        // end
        
	end

  //clock 
	always 
	begin
		#5	clk = ~clk;
	end

	//running
	initial
	begin
        clk = 1'b1;
        #1
        reset <= 1'b1;

        #1
        reset <= 1'b0;

        #5 
        address <= 32'b100000000000000000000001_1001_10_10;

        c_read_i <= 1'b1;

        c_wr_i <= 1'b0;
        
        #10
        address <= 32'd2;

        #10
        reset <= 1'b1;

        #10

        $finish;

	end
		 
endmodule

verilog/testbench/wavedata.vcd
$date
	Sun Jan 14 10:35:05 2024
$end
$version
	Icarus Verilog
$end
$timescale
	1ps
$end
$scope module testcache $end
$var wire 32 ! data [31:0] $end
$var wire 1 " busywait $end
$var parameter 32 # line_size $end
$var reg 32 $ address [31:0] $end
$var reg 1 % c_read_i $end
$var reg 1 & c_wr_i $end
$var reg 1 ' clk $end
$var reg 1 ( reset $end
$scope module mycache $end
$var wire 32 ) address_i [31:0] $end
$var wire 1 % c_read_i $end
$var wire 1 & c_wr_i $end
$var wire 1 ' clk_i $end
$var wire 1 * is_dirty $end
$var wire 1 ( reset_i $end
$var wire 24 + tag_addr [23:0] $end
$var wire 2 , offset_addr [1:0] $end
$var wire 4 - index_addr [3:0] $end
$var parameter 32 . c_assiotivity $end
$var parameter 32 / c_block_size $end
$var parameter 32 0 c_index $end
$var parameter 32 1 c_line_size $end
$var parameter 35 2 c_tag_size $end
$var reg 1 " c_busywait_o $end
$var reg 32 3 c_data_o [31:0] $end
$var reg 1 4 c_hit $end
$var integer 32 5 i [31:0] $end
$var integer 32 6 j [31:0] $end
$var integer 32 7 less_used_assiotivity [31:0] $end
$upscope $end
$upscope $end
$scope module testcache $end
$scope module mycache $end
$var reg 1 8 \c_valid_bit[36] $end
$upscope $end
$upscope $end
$scope module testcache $end
$scope module mycache $end
$var reg 1 9 \c_valid_bit[37] $end
$upscope $end
$upscope $end
$scope module testcache $end
$scope module mycache $end
$var reg 24 : \c_tag[36] [23:0] $end
$upscope $end
$upscope $end
$scope module testcache $end
$scope module mycache $end
$var reg 24 ; \c_tag[37] [23:0] $end
$upscope $end
$upscope $end
$scope module testcache $end
$scope module mycache $end
$var reg 32 < \c_word[148] [31:0] $end
$upscope $end
$upscope $end
$scope module testcache $end
$scope module mycache $end
$var reg 32 = \c_word[149] [31:0] $end
$upscope $end
$upscope $end
$scope module testcache $end
$scope module mycache $end
$var reg 32 > \c_word[150] [31:0] $end
$upscope $end
$upscope $end
$scope module testcache $end
$scope module mycache $end
$var reg 32 ? \c_word[151] [31:0] $end
$upscope $end
$upscope $end
$scope module testcache $end
$scope module mycache $end
$var reg 1 @ \valid_bit_frm_c[0] $end
$upscope $end
$upscope $end
$scope module testcache $end
$scope module mycache $end
$var reg 1 A \valid_bit_frm_c[1] $end
$upscope $end
$upscope $end
$scope module testcache $end
$scope module mycache $end
$var reg 1 B \valid_bit_frm_c[2] $end
$upscope $end
$upscope $end
$scope module testcache $end
$scope module mycache $end
$var reg 1 C \valid_bit_frm_c[3] $end
$upscope $end
$upscope $end
$scope module testcache $end
$scope module mycache $end
$var reg 24 D \tag_frm_c[0] [23:0] $end
$upscope $end
$upscope $end
$scope module testcache $end
$scope module mycache $end
$var reg 24 E \tag_frm_c[1] [23:0] $end
$upscope $end
$upscope $end
$scope module testcache $end
$scope module mycache $end
$var reg 24 F \tag_frm_c[2] [23:0] $end
$upscope $end
$upscope $end
$scope module testcache $end
$scope module mycache $end
$var reg 24 G \tag_frm_c[3] [23:0] $end
$upscope $end
$upscope $end
$scope module testcache $end
$scope module mycache $end
$var reg 1 H \hit_frm_c[0] $end
$upscope $end
$upscope $end
$scope module testcache $end
$scope module mycache $end
$var reg 1 I \hit_frm_c[1] $end
$upscope $end
$upscope $end
$scope module testcache $end
$scope module mycache $end
$var reg 1 J \hit_frm_c[2] $end
$upscope $end
$upscope $end
$scope module testcache $end
$scope module mycache $end
$var reg 1 K \hit_frm_c[3] $end
$upscope $end
$upscope $end
$scope module testcache $end
$scope module mycache $end
$var reg 1 L \hit_frm_c_AND_valid_bit_frm_c[0] $end
$upscope $end
$upscope $end
$scope module testcache $end
$scope module mycache $end
$var reg 1 M \hit_frm_c_AND_valid_bit_frm_c[1] $end
$upscope $end
$upscope $end
$scope module testcache $end
$scope module mycache $end
$var reg 1 N \hit_frm_c_AND_valid_bit_frm_c[2] $end
$upscope $end
$upscope $end
$scope module testcache $end
$scope module mycache $end
$var reg 1 O \hit_frm_c_AND_valid_bit_frm_c[3] $end
$upscope $end
$upscope $end
$scope module testcache $end
$scope module mycache $end
$var reg 32 P \data_frm_c[0] [31:0] $end
$upscope $end
$upscope $end
$scope module testcache $end
$scope module mycache $end
$var reg 32 Q \data_frm_c[1] [31:0] $end
$upscope $end
$upscope $end
$scope module testcache $end
$scope module mycache $end
$var reg 32 R \data_frm_c[2] [31:0] $end
$upscope $end
$upscope $end
$scope module testcache $end
$scope module mycache $end
$var reg 32 S \data_frm_c[3] [31:0] $end
$upscope $end
$upscope $end
$scope module testcache $end
$scope module mycache $end
$var reg 3 T \usability_bit_frm_c[0] [2:0] $end
$upscope $end
$upscope $end
$scope module testcache $end
$scope module mycache $end
$var reg 3 U \usability_bit_frm_c[1] [2:0] $end
$upscope $end
$upscope $end
$scope module testcache $end
$scope module mycache $end
$var reg 3 V \usability_bit_frm_c[2] [2:0] $end
$upscope $end
$upscope $end
$scope module testcache $end
$scope module mycache $end
$var reg 3 W \usability_bit_frm_c[3] [2:0] $end
$upscope $end
$upscope $end
$enddefinitions $end
$comment Show the parameter values. $end
$dumpall
b11000 2
b100000 1
b100 0
b10 /
b10 .
b100000 #
$end
#0
$dumpvars
bx W
bx V
bx U
bx T
bx S
bx R
bx Q
bx P
xO
xN
xM
xL
1K
1J
1I
1H
bx G
bx F
bx E
bx D
xC
xB
xA
x@
bx ?
bx >
b11 =
bx <
b100000000000000000000001 ;
bx :
19
x8
bx 7
b100 6
b100 5
04
bx 3
bx -
bx ,
bx +
x*
bx )
x(
1'
x&
x%
bx $
x"
bx !
$end
#1000
bx W
bx S
xO
1K
bx G
xC
bx V
bx R
xN
1J
bx F
xB
bx U
bx Q
xM
1I
bx E
xA
bx T
bx P
xL
1H
bx D
x@
b0 ;
b0 ?
b0 >
b0 =
b0 <
09
b0 :
08
b100 6
b100 5
1(
#2000
bx W
bx S
xO
1K
bx G
xC
bx V
bx R
xN
1J
bx F
xB
bx U
bx Q
xM
1I
bx E
xA
bx T
bx P
xL
1H
bx D
x@
b11 =
b100000000000000000000001 ;
19
b100 6
b100 5
0(
#5000
0'
#7000
0*
b0 7
b100 W
b0 S
0O
0K
b0 G
0C
b1 V
b0 R
0N
0J
b0 F
0B
b0 !
b0 3
14
b10 U
b0 Q
1M
1I
b100000000000000000000001 E
1A
b1 T
b0 P
0L
0H
b0 D
0@
b100 5
b10 ,
b1001 -
b100000000000000000000001 +
0&
1%
b10000000000000000000000110011010 $
b10000000000000000000000110011010 )
#10000
b11 =
b100000000000000000000001 ;
19
b100 6
b10000 5
1'
#15000
0'
#17000
b0 W
b0 S
0O
1K
b0 G
0C
b0 V
b0 R
0N
1J
b0 F
0B
b0 U
b0 Q
0M
1I
b0 E
0A
b0 T
b0 P
0L
1H
b0 D
0@
b100 5
04
b0 ,
b0 -
b0 +
b10 $
b10 )
#20000
b11 =
b100000000000000000000001 ;
19
b100 6
b10000 5
1'
#25000
0'
#27000
b0 W
b0 S
0O
1K
b0 G
0C
b0 V
b0 R
0N
1J
b0 F
0B
b0 U
b0 Q
0M
1I
b0 E
0A
b0 T
b0 P
0L
1H
b0 D
0@
b0 ;
b0 ?
b0 >
b0 =
b0 <
09
b0 :
08
b100 6
b100 5
1(
#30000
b0 ;
b0 ?
b0 >
b0 =
b0 <
09
b0 :
08
b100 6
b10000 5
1'
