verilog/modules/memory.v
module memory (
    m_busywait_o, m_read_data_o, m_write_done, m_read_done, m_clk_i, m_reset_i, m_read_i, m_wr_i, m_addr_i, m_wr_data_i
);

    parameter  c_block_size = 2, c_line_size = 32, address_size = 32, mem_line_size = 32;

    input m_clk_i, m_read_i, m_wr_i, m_reset_i;
    input [address_size - c_block_size - 3:0] m_addr_i;
    input [2**c_block_size*c_line_size - 1 : 0] m_wr_data_i;

    output reg [2**c_block_size*c_line_size - 1 : 0] m_read_data_o;
    output reg m_busywait_o;
    output reg m_write_done, m_read_done;

    reg [c_block_size - 1:0] byte_read_count;

    reg [mem_line_size - 1:0] memory [0:2047];

    reg [2**c_block_size*c_line_size - 1 : 0] data_to_be_write;

    // assign data_to_be_write = m_wr_data_i[mem_line_size * byte_read_count - 1 : mem_line_size * (byte_read_count - 1)];


    // wire mem_access;

    // assign mem_access <= (m_read_i || m_wr_data_i);

    initial begin
        $readmemh("../modules/mem.data", memory);
    end

    // assign m_read_data_o = {memory[0], memory[1], memory[2], memory[3]};
    // assign m_busywait_o = 1'b0;

    // always @(*posedge m_clk_i) begin
    //     m_busywait_o <= mem_access ? 1'b1 : 1'b0;

    // end


    //
    // always @(posedge m_clk_i, m_busywait_o) begin
    //     if(m_busywait_o) byte_read_count = byte_read_count + 1;
    // end

    parameter IDLE = 3'b000, MEM_READ = 3'b001, MEM_WRITE = 3'b010, MEM_READ_DONE = 3'b011, MEM_WRITE_DONE = 3'b100;

    reg [2:0] m_state, m_n_state;
    //control signals based on state
    always @(*) begin
        case (m_state)
            IDLE: begin
                m_busywait_o = 1'b0;
                m_write_done = 1'b0;
                m_read_done = 1'b0;
            end
            MEM_READ: begin
                m_busywait_o = 1'b1;
                m_write_done = 1'b0;
                m_read_done = 1'b0;
                // m_read_data_o[mem_line_size * byte_read_count - 1 : mem_line_size * (byte_read_count - 1)] = memory[{m_addr_i, byte_read_count}];
                // m_read_data_o = {memory[{m_addr_i, byte_read_count}], };

            end
            MEM_WRITE: begin
                m_busywait_o = 1'b1;
                m_write_done = 1'b0;
                m_read_done = 1'b0;
                // memory[{m_addr_i, byte_read_count}] = m_wr_data_i[mem_line_size * byte_read_count - 1 : mem_line_size * (byte_read_count - 1)];
            end
            MEM_READ_DONE: begin
                m_busywait_o = 1'b0;
                m_write_done = 1'b0;
                m_read_done = 1'b1;
            end
            MEM_WRITE_DONE: begin
                m_busywait_o = 1'b0;
                m_write_done = 1'b1;
                m_read_done = 1'b0;
            end
        endcase
    end

    always @(posedge m_clk_i) begin
        case (m_state)
            IDLE: begin
                data_to_be_write = m_wr_data_i;
            end
            MEM_READ: begin
                m_read_data_o = m_read_data_o >> mem_line_size;
                m_read_data_o[2**c_block_size*c_line_size - 1 : 2**c_block_size*c_line_size - mem_line_size] = memory[{m_addr_i, byte_read_count}];
            end
            MEM_WRITE: begin
                memory[{m_addr_i, byte_read_count}] = data_to_be_write[mem_line_size - 1:0];
                data_to_be_write = data_to_be_write >> mem_line_size;
                //m_wr_data_i[mem_line_size * byte_read_count - 1 : mem_line_size * (byte_read_count - 1)];
                // m_wr_data_i = m_wr_data_i >> m_wr_data_i;                
            end
        endcase
    end

    //state transission
    always @(*) begin
        case (m_state)
            IDLE: begin
                if(m_read_i) m_n_state = MEM_READ;
                else if (m_wr_i) m_n_state = MEM_WRITE;
            end
            MEM_READ: begin
                if(&byte_read_count) m_n_state = MEM_READ_DONE;
            end
            MEM_WRITE: begin
                if(&byte_read_count) m_n_state = MEM_WRITE_DONE;
            end
            MEM_READ_DONE: begin
                m_n_state = IDLE;
            end
            MEM_WRITE_DONE: begin
                m_n_state = IDLE;
            end

        endcase
    end

    //change state
    always @(posedge m_clk_i, posedge m_reset_i) begin
        if (m_reset_i) begin
            m_state = IDLE;
            m_n_state = IDLE;
        end
        else m_state <= m_n_state;
    end


    //counter
    always @(posedge m_clk_i) begin
        case (m_state)
            IDLE: byte_read_count = 0;
            MEM_READ: byte_read_count = byte_read_count + 1;
            MEM_WRITE: byte_read_count = byte_read_count + 1;
            MEM_READ_DONE: byte_read_count = 0;
            MEM_WRITE_DONE: byte_read_count = 0;
        endcase
    end
    
endmodule

verilog/modules/cache.v
// `include "./memory.v"

module cache (
    c_busywait_o, c_data_o, c_m_write_data_o, c_m_read_o, c_m_wr_o, c_m_address_o, reset_i, clk_i, address_i, c_read_i, c_wr_i, c_m_busywait_i, c_m_read_data_i, m_write_done, m_read_done
);

    parameter c_line_size = 32, c_assiotivity = 2, c_index = 4, c_block_size = 2, address_size = 32; // cache line size, assiotivity, index size, block size
    parameter c_tag_size = c_line_size - c_index - c_block_size - 2;
    // parameter c_block_size = c_line_size*(2**c_block_size);
    integer i, j;

    input reset_i, clk_i, c_read_i, c_wr_i;
    input [address_size - 1:0] address_i;

    //for data memory from cache
    output reg c_m_read_o, c_m_wr_o;
    output reg [2**c_block_size*c_line_size - 1:0] c_m_write_data_o;
    output reg [address_size - c_block_size - 3:0] c_m_address_o;
    input [2**c_block_size*c_line_size - 1:0] c_m_read_data_i;
    input c_m_busywait_i, m_write_done, m_read_done;


    output reg [c_line_size - 1:0] c_data_o;
    output reg c_busywait_o;


    reg [2**c_block_size*c_line_size - 1 : 0] c_word[0 : (2**c_index) - 1][0 : (2**c_assiotivity) - 1]; //cache word
    reg [c_tag_size - 1 : 0] c_tag[0 : (2**c_index) - 1][0 : (2**c_assiotivity) - 1];  //cache tag
    reg c_valid_bit [0 : (2**c_index) - 1][0 : (2**c_assiotivity) - 1]; //cache valid bit
    reg c_dirty_bit [0 : (2**c_index) - 1][0 : (2**c_assiotivity) - 1]; //cache dirty bit
    reg [2:0] c_usability_bit [0 : (2**c_index) - 1][0 : (2**c_assiotivity) - 1]; //cache dirty bit

    wire [c_block_size - 1:0] offset_addr;
    wire [c_index - 1:0] index_addr;
    wire [c_tag_size - 1:0] tag_addr;


    reg valid_bit_frm_c [0 : (2**c_assiotivity) - 1];
    reg hit_frm_c [0 : (2**c_assiotivity) - 1];
    reg hit_frm_c_AND_valid_bit_frm_c [0 : (2**c_assiotivity) - 1];
    reg dirty_bit_frm_c [0 : (2**c_assiotivity) - 1];
    reg [c_tag_size - 1 : 0] tag_frm_c [0 : (2**c_assiotivity) - 1];
    reg [c_line_size - 1 : 0] data_frm_c [0 : (2**c_assiotivity) - 1];
    reg [2:0] usability_bit_frm_c [0 : (2**c_assiotivity) - 1];

    reg [c_assiotivity - 1 : 0] hit_cache_assiotivity;
    reg c_hit;


    //{tag_addr:}{index_addr:}{offset_addr:}{2}
    assign offset_addr = address_i[c_block_size + 1:2];
    assign index_addr = address_i[c_index + c_block_size + 1:c_block_size + 2];
    assign tag_addr = address_i[c_line_size - 1:c_index + c_block_size + 2];

    // reg [c_block_size - 1:0] offset_addr_tmp;
    
    // always @(*) begin
    //     offset_addr_tmp = offset_addr;
        
    // end

    //
    wire [address_size - c_block_size - 3:0] c_m_address_read, c_m_address_wr;

    //address for data memeory
    assign c_m_address_read = {address_i[address_size : c_block_size + 2]};

    assign c_m_address_wr = tag_frm_c[less_used_assiotivity];

    //data for mem write
    // assign c_m_write_data_o = data_frm_c[less_used_assiotivity];


    //read data, valid bit, check tag == cache tag from cache sets
    // integer offset = offset_addr*c_line_size;
    // integer tmp;
    // always @(posedge clk) begin
    //     tmp = offset_addr*c_line_size;
    // end

    always @(*) begin
        c_hit = 1'b0;
        for (i = 0; i < 2**c_assiotivity; i = i + 1) begin
            valid_bit_frm_c[i] = c_valid_bit[index_addr][i];
            tag_frm_c[i] = c_tag[index_addr][i];
            dirty_bit_frm_c[i] = c_dirty_bit[index_addr][i];
            hit_frm_c[i] = (tag_addr === tag_frm_c[i]) ? 1'b1 : 1'b0;
            hit_frm_c_AND_valid_bit_frm_c[i] = valid_bit_frm_c[i] && hit_frm_c[i];
            data_frm_c[i] = c_word[index_addr][i] >> (offset_addr * c_line_size);
            usability_bit_frm_c[i] = c_usability_bit[index_addr][i];

            if (hit_frm_c_AND_valid_bit_frm_c[i]) begin
                c_hit = 1'b1;
                c_data_o = data_frm_c[i];
            end
        end
    end

    //select less used cache assiotivity
    integer less_used_assiotivity;
    always @(*) begin
        less_used_assiotivity = 0;
        for (i = 1; i < 2**c_assiotivity; i = i + 1) begin
            if (usability_bit_frm_c[less_used_assiotivity] > usability_bit_frm_c[i]) less_used_assiotivity = i;
        end
    end

    //dirty bit wire
    wire is_dirty;
    assign is_dirty = dirty_bit_frm_c[less_used_assiotivity];

    // //busy wait
    // always @(*) begin
    //     if (!c_hit & (c_read_i | c_wr_i)) 
    //         c_busywait_o = 1'b1;
    //     else
    //         c_busywait_o = 1'b0;
    // end

    always @(posedge clk_i, reset_i)
    begin
        if(reset_i)
        begin
            for (i = 0; i < 2**c_index; i = i + 1) begin
                for (j = 0; j < 2**c_assiotivity; j = j + 1) begin
                    c_valid_bit[i][j] = 0;
                    c_word[i][j] = 0;
                    // c_word[i][j][1] = 0;
                    // c_word[i][j][2] = 0;
                    // c_word[i][j][3] = 0;
                    c_tag[i][j] = 0;
                    c_dirty_bit[i][j] = 0;
                    c_usability_bit[i][j] = 0;
                end
            end
        end
        else
        begin
            //need to integreate
            // for (i = 0; i < 2**c_index; i = i + 1) begin
            //     for (j = 0; j < 2**c_assiotivity; j = j + 1) begin
            //         c_valid_bit[9][1] = 0;
            //         c_dirty_bit[9][1] = 1;
            //         c_tag[9][1] = 24'h800001;
            //         c_word[9][1][95:64] = 32'd11;
            //         c_word[9][0][95:63] = 32'd11;
            //         c_usability_bit[9][0] = 3'd1;
            //         c_usability_bit[9][1] = 3'd2;
            //         c_usability_bit[9][2] = 3'd1;
            //         c_usability_bit[9][3] = 3'd4;
            //     end
            // end

            if(c_allow_wr) begin
                c_valid_bit[index_addr][less_used_assiotivity] = 1'b1;
                c_tag[index_addr][less_used_assiotivity] = c_m_address_read;
                c_word[index_addr][less_used_assiotivity] = c_m_read_data_i;

                c_usability_bit[index_addr][less_used_assiotivity] = 3'd1;
                c_usability_bit[index_addr][less_used_assiotivity] = 3'd2;
                c_usability_bit[index_addr][less_used_assiotivity] = 3'd1;
                c_usability_bit[index_addr][less_used_assiotivity] = 3'd4;
                // for (i = 0; i < 2**c_block_size; i = i + 1) begin
                //     c_word[index_addr][less_used_assiotivity][i] = c_m_read_data_i[(i+1)*c_line_size : i*c_line_size];
                // end

            end
        end
    end
    
    //state machine
    parameter IDLE = 3'b000, MEM_READ = 3'b001, MEM_WRITE = 3'b010, MEM_READ_DONE = 3'b011, MEM_WRITE_DONE = 3'b100;   //, CACHE_WRITE_BACK = 3'b011;
    reg [2:0] c_state, c_n_state;
    reg c_allow_wr;

    //state transisstion
    always @(*)
    begin
        case (c_state)
            IDLE: begin
                if(!c_hit && (c_read_i || c_wr_i) && is_dirty) begin
                    c_n_state <= MEM_WRITE;
                end
                else if (!c_hit && (c_read_i || c_wr_i) && !is_dirty) begin
                    c_n_state <= MEM_READ;
                end
                else
                    c_n_state <= IDLE;
            end
            MEM_READ: begin
                if(!c_m_busywait_i && m_read_done) c_n_state = MEM_READ_DONE;
            end
            MEM_WRITE: begin
                if(!c_m_busywait_i && m_write_done) c_n_state = MEM_WRITE_DONE;
            end
            MEM_READ_DONE: begin
                c_n_state = IDLE;
            end
            MEM_WRITE_DONE: begin
                c_n_state = IDLE;
            end
        endcase
    end

    //combination logic for cache control signals
    always @(*)
    begin
        case (c_state)
            IDLE: begin
                c_busywait_o <= 1'b0;
                c_m_read_o <= 1'b0;
                c_m_wr_o <= 1'b0;
                c_allow_wr <= 1'b0;
                c_m_address_o = c_m_address_read;
            end
            MEM_READ: begin
                c_busywait_o <= 1'b1;
                c_m_read_o <= m_read_done ? 1'b0 : 1'b1;
                c_m_wr_o <= 1'b0;
                c_allow_wr <= 1'b0;
                c_m_address_o = c_m_address_read;
            end
            MEM_WRITE: begin
                c_busywait_o <= 1'b1;
                c_m_read_o <= 1'b0;
                c_m_wr_o <= m_write_done ? 1'b0 : 1'b1;;
                c_allow_wr <= 1'b0;
                c_m_address_o = c_m_address_wr;
                c_m_write_data_o = data_frm_c[less_used_assiotivity];
            end
            MEM_READ_DONE: begin
                c_busywait_o <= 1'b1;
                c_m_read_o <= 1'b0;
                c_m_wr_o <= 1'b0;
                c_allow_wr <= 1'b1;
                c_m_address_o = c_m_address_read;
            end
            MEM_WRITE_DONE: begin
                c_busywait_o <= 1'b1;
                c_m_read_o <= 1'b0;
                c_m_wr_o <= 1'b0;
                c_allow_wr <= 1'b0;
                c_m_address_o = c_m_address_read;
            end
        endcase
    end

    //cache state change
    always @(posedge clk_i, posedge reset_i) begin
        if (reset_i) c_state <= IDLE;
        else c_state <= c_n_state;
    end

endmodule

verilog/testbench/cache_tb.v
`timescale 1ns/1ps

`include "../modules/cache.v"
`include "../modules/memory.v"


module testcache;

    // input reset, clk;
    // input [line_size - 1:0] address;

    // output reg [line_size - 1:0] data;
    // output busywait;
    parameter  c_block_size = 2, c_line_size = 32, address_size = 32;

    wire c_busywait_o;
    wire [c_line_size - 1:0] c_data_o;
    reg [address_size - 1:0] address;
    reg clk, reset, c_read_i, c_wr_i;
    integer i,j;
    
    wire c_m_busywait_i, c_m_read_o, c_m_wr_o, m_write_done, m_read_done;
    wire [2**c_block_size*c_line_size - 1 : 0] c_m_read_data_i;
    wire [2**c_block_size*c_line_size - 1 : 0] c_m_write_data_o;
    wire [address_size - c_block_size - 3:0] c_m_address_o;

    //c_busywait_o, c_data_o, c_m_write_data_o, c_m_read_o, c_m_wr_o, c_m_address_o, reset_i, clk_i, address_i, c_read_i, c_wr_i, c_m_busywait_i, c_m_read_data_i
    cache mycache(c_busywait_o, c_data_o, c_m_write_data_o, c_m_read_o, c_m_wr_o, c_m_address_o, reset, clk, address, c_read_i, c_wr_i, c_m_busywait_i, c_m_read_data_i, m_write_done, m_read_done);
    //memory module connect
    memory data_memory(c_m_busywait_i, c_m_read_data_i, m_write_done, m_read_done, clk, reset, c_m_read_o, c_m_wr_o, c_m_address_o, c_m_write_data_o);
    //m_busywait_o, m_read_data_o, m_clk_i, m_read_i, m_wr_i, m_reset_i, m_addr_i, m_wr_data_i


	//wavedata file
	initial
	begin
		$dumpfile("wavedata.vcd");
		$dumpvars(0,testcache);
        // $dumpvars(0, mycache.tag_reg[0]);
    
        // for(i = 0; i < 4; i = i + 1)begin
        //     // $dumpvars(0, mycache.c_valid_bit[1][i]);
        //     $dumpvars(0, mycache.c_valid_bit[9][i]);
        // end
        $dumpvars(0, mycache.c_valid_bit[9][0]);
        $dumpvars(0, mycache.c_valid_bit[9][1]);

        $dumpvars(0, mycache.c_tag[9][0]);
        $dumpvars(0, mycache.c_tag[9][1]);

        $dumpvars(0, mycache.c_word[9][1]);

        $dumpvars(0, mycache.c_usability_bit[9][1]);

        $dumpvars(0, mycache.c_dirty_bit[9][1]);

        $dumpvars(0, mycache.valid_bit_frm_c[0]);
        $dumpvars(0, mycache.valid_bit_frm_c[1]);
        $dumpvars(0, mycache.valid_bit_frm_c[2]);
        $dumpvars(0, mycache.valid_bit_frm_c[3]);

        $dumpvars(0, mycache.tag_frm_c[0]);
        $dumpvars(0, mycache.tag_frm_c[1]);
        $dumpvars(0, mycache.tag_frm_c[2]);
        $dumpvars(0, mycache.tag_frm_c[3]);

        $dumpvars(0, mycache.hit_frm_c[0]);
        $dumpvars(0, mycache.hit_frm_c[1]);
        $dumpvars(0, mycache.hit_frm_c[2]);
        $dumpvars(0, mycache.hit_frm_c[3]);

        $dumpvars(0, mycache.hit_frm_c_AND_valid_bit_frm_c[0]);
        $dumpvars(0, mycache.hit_frm_c_AND_valid_bit_frm_c[1]);
        $dumpvars(0, mycache.hit_frm_c_AND_valid_bit_frm_c[2]);
        $dumpvars(0, mycache.hit_frm_c_AND_valid_bit_frm_c[3]);

        $dumpvars(0, mycache.data_frm_c[0]);
        $dumpvars(0, mycache.data_frm_c[1]);
        $dumpvars(0, mycache.data_frm_c[2]);
        $dumpvars(0, mycache.data_frm_c[3]);

        $dumpvars(0, mycache.usability_bit_frm_c[0]);
        $dumpvars(0, mycache.usability_bit_frm_c[1]);
        $dumpvars(0, mycache.usability_bit_frm_c[2]);
        $dumpvars(0, mycache.usability_bit_frm_c[3]);

        $dumpvars(0, mycache.dirty_bit_frm_c[0]);
        $dumpvars(0, mycache.dirty_bit_frm_c[1]);
        $dumpvars(0, mycache.dirty_bit_frm_c[2]);
        $dumpvars(0, mycache.dirty_bit_frm_c[3]);

        // for(i = 0; i < 2; i = i + 1)begin
        //     // $dumpvars(0, mycache.c_valid_bit[1][i]);
        //     $dumpvars(0, mycache.valid_bit_frm_c[i]);
        //     $dumpvars(0, mycache.tag_frm_c[i]);
        //     $dumpvars(0, mycache.hit_frm_c[i]);
        //     $dumpvars(0, mycache.hit_frm_c_AND_valid_bit_frm_c[i]);
        //     $dumpvars(0, mycache.data_frm_c[i]);
        // end
        
	end

  //clock 
	always 
	begin
		#5	clk = ~clk;
	end

	//running
	initial
	begin
        clk = 1'b1;
        #1
        reset <= 1'b1;

        #1
        reset <= 1'b0;

        #5 
        address <= 32'b000000000000000000000000_0000_10_10;

        c_read_i <= 1'b1;

        c_wr_i <= 1'b0;
        
        #10
        address <= 32'd2;

        #10
        // reset <= 1'b1;

        #10
        #10
        #10
        #10
        #10
        #10
        #10

        $finish;

	end
		 
endmodule

verilog/testbench/wavedata.vcd
$date
	Tue Jan 16 19:17:58 2024
$end
$version
	Icarus Verilog
$end
$timescale
	1ps
$end
$scope module testcache $end
$var wire 1 ! m_write_done $end
$var wire 1 " m_read_done $end
$var wire 128 # c_m_write_data_o [127:0] $end
$var wire 1 $ c_m_wr_o $end
$var wire 1 % c_m_read_o $end
$var wire 128 & c_m_read_data_i [127:0] $end
$var wire 1 ' c_m_busywait_i $end
$var wire 28 ( c_m_address_o [27:0] $end
$var wire 32 ) c_data_o [31:0] $end
$var wire 1 * c_busywait_o $end
$var parameter 32 + address_size $end
$var parameter 32 , c_block_size $end
$var parameter 32 - c_line_size $end
$var reg 32 . address [31:0] $end
$var reg 1 / c_read_i $end
$var reg 1 0 c_wr_i $end
$var reg 1 1 clk $end
$var reg 1 2 reset $end
$scope module data_memory $end
$var wire 1 1 m_clk_i $end
$var wire 1 2 m_reset_i $end
$var wire 1 $ m_wr_i $end
$var wire 128 3 m_wr_data_i [127:0] $end
$var wire 1 % m_read_i $end
$var wire 28 4 m_addr_i [27:0] $end
$var parameter 3 5 IDLE $end
$var parameter 3 6 MEM_READ $end
$var parameter 3 7 MEM_READ_DONE $end
$var parameter 3 8 MEM_WRITE $end
$var parameter 3 9 MEM_WRITE_DONE $end
$var parameter 32 : address_size $end
$var parameter 32 ; c_block_size $end
$var parameter 32 < c_line_size $end
$var parameter 32 = mem_line_size $end
$var reg 2 > byte_read_count [1:0] $end
$var reg 128 ? data_to_be_write [127:0] $end
$var reg 1 ' m_busywait_o $end
$var reg 3 @ m_n_state [2:0] $end
$var reg 128 A m_read_data_o [127:0] $end
$var reg 1 " m_read_done $end
$var reg 3 B m_state [2:0] $end
$var reg 1 ! m_write_done $end
$upscope $end
$scope module mycache $end
$var wire 32 C address_i [31:0] $end
$var wire 1 ' c_m_busywait_i $end
$var wire 128 D c_m_read_data_i [127:0] $end
$var wire 1 / c_read_i $end
$var wire 1 0 c_wr_i $end
$var wire 1 1 clk_i $end
$var wire 1 E is_dirty $end
$var wire 1 " m_read_done $end
$var wire 1 ! m_write_done $end
$var wire 1 2 reset_i $end
$var wire 24 F tag_addr [23:0] $end
$var wire 2 G offset_addr [1:0] $end
$var wire 4 H index_addr [3:0] $end
$var wire 28 I c_m_address_wr [27:0] $end
$var wire 28 J c_m_address_read [27:0] $end
$var parameter 3 K IDLE $end
$var parameter 3 L MEM_READ $end
$var parameter 3 M MEM_READ_DONE $end
$var parameter 3 N MEM_WRITE $end
$var parameter 3 O MEM_WRITE_DONE $end
$var parameter 32 P address_size $end
$var parameter 32 Q c_assiotivity $end
$var parameter 32 R c_block_size $end
$var parameter 32 S c_index $end
$var parameter 32 T c_line_size $end
$var parameter 35 U c_tag_size $end
$var reg 1 V c_allow_wr $end
$var reg 1 * c_busywait_o $end
$var reg 32 W c_data_o [31:0] $end
$var reg 1 X c_hit $end
$var reg 28 Y c_m_address_o [27:0] $end
$var reg 1 % c_m_read_o $end
$var reg 1 $ c_m_wr_o $end
$var reg 128 Z c_m_write_data_o [127:0] $end
$var reg 3 [ c_n_state [2:0] $end
$var reg 3 \ c_state [2:0] $end
$var integer 32 ] i [31:0] $end
$var integer 32 ^ j [31:0] $end
$var integer 32 _ less_used_assiotivity [31:0] $end
$upscope $end
$upscope $end
$scope module testcache $end
$scope module mycache $end
$var reg 1 ` \c_valid_bit[36] $end
$upscope $end
$upscope $end
$scope module testcache $end
$scope module mycache $end
$var reg 1 a \c_valid_bit[37] $end
$upscope $end
$upscope $end
$scope module testcache $end
$scope module mycache $end
$var reg 24 b \c_tag[36] [23:0] $end
$upscope $end
$upscope $end
$scope module testcache $end
$scope module mycache $end
$var reg 24 c \c_tag[37] [23:0] $end
$upscope $end
$upscope $end
$scope module testcache $end
$scope module mycache $end
$var reg 128 d \c_word[37] [127:0] $end
$upscope $end
$upscope $end
$scope module testcache $end
$scope module mycache $end
$var reg 3 e \c_usability_bit[37] [2:0] $end
$upscope $end
$upscope $end
$scope module testcache $end
$scope module mycache $end
$var reg 1 f \c_dirty_bit[37] $end
$upscope $end
$upscope $end
$scope module testcache $end
$scope module mycache $end
$var reg 1 g \valid_bit_frm_c[0] $end
$upscope $end
$upscope $end
$scope module testcache $end
$scope module mycache $end
$var reg 1 h \valid_bit_frm_c[1] $end
$upscope $end
$upscope $end
$scope module testcache $end
$scope module mycache $end
$var reg 1 i \valid_bit_frm_c[2] $end
$upscope $end
$upscope $end
$scope module testcache $end
$scope module mycache $end
$var reg 1 j \valid_bit_frm_c[3] $end
$upscope $end
$upscope $end
$scope module testcache $end
$scope module mycache $end
$var reg 24 k \tag_frm_c[0] [23:0] $end
$upscope $end
$upscope $end
$scope module testcache $end
$scope module mycache $end
$var reg 24 l \tag_frm_c[1] [23:0] $end
$upscope $end
$upscope $end
$scope module testcache $end
$scope module mycache $end
$var reg 24 m \tag_frm_c[2] [23:0] $end
$upscope $end
$upscope $end
$scope module testcache $end
$scope module mycache $end
$var reg 24 n \tag_frm_c[3] [23:0] $end
$upscope $end
$upscope $end
$scope module testcache $end
$scope module mycache $end
$var reg 1 o \hit_frm_c[0] $end
$upscope $end
$upscope $end
$scope module testcache $end
$scope module mycache $end
$var reg 1 p \hit_frm_c[1] $end
$upscope $end
$upscope $end
$scope module testcache $end
$scope module mycache $end
$var reg 1 q \hit_frm_c[2] $end
$upscope $end
$upscope $end
$scope module testcache $end
$scope module mycache $end
$var reg 1 r \hit_frm_c[3] $end
$upscope $end
$upscope $end
$scope module testcache $end
$scope module mycache $end
$var reg 1 s \hit_frm_c_AND_valid_bit_frm_c[0] $end
$upscope $end
$upscope $end
$scope module testcache $end
$scope module mycache $end
$var reg 1 t \hit_frm_c_AND_valid_bit_frm_c[1] $end
$upscope $end
$upscope $end
$scope module testcache $end
$scope module mycache $end
$var reg 1 u \hit_frm_c_AND_valid_bit_frm_c[2] $end
$upscope $end
$upscope $end
$scope module testcache $end
$scope module mycache $end
$var reg 1 v \hit_frm_c_AND_valid_bit_frm_c[3] $end
$upscope $end
$upscope $end
$scope module testcache $end
$scope module mycache $end
$var reg 32 w \data_frm_c[0] [31:0] $end
$upscope $end
$upscope $end
$scope module testcache $end
$scope module mycache $end
$var reg 32 x \data_frm_c[1] [31:0] $end
$upscope $end
$upscope $end
$scope module testcache $end
$scope module mycache $end
$var reg 32 y \data_frm_c[2] [31:0] $end
$upscope $end
$upscope $end
$scope module testcache $end
$scope module mycache $end
$var reg 32 z \data_frm_c[3] [31:0] $end
$upscope $end
$upscope $end
$scope module testcache $end
$scope module mycache $end
$var reg 3 { \usability_bit_frm_c[0] [2:0] $end
$upscope $end
$upscope $end
$scope module testcache $end
$scope module mycache $end
$var reg 3 | \usability_bit_frm_c[1] [2:0] $end
$upscope $end
$upscope $end
$scope module testcache $end
$scope module mycache $end
$var reg 3 } \usability_bit_frm_c[2] [2:0] $end
$upscope $end
$upscope $end
$scope module testcache $end
$scope module mycache $end
$var reg 3 ~ \usability_bit_frm_c[3] [2:0] $end
$upscope $end
$upscope $end
$scope module testcache $end
$scope module mycache $end
$var reg 1 !" \dirty_bit_frm_c[0] $end
$upscope $end
$upscope $end
$scope module testcache $end
$scope module mycache $end
$var reg 1 "" \dirty_bit_frm_c[1] $end
$upscope $end
$upscope $end
$scope module testcache $end
$scope module mycache $end
$var reg 1 #" \dirty_bit_frm_c[2] $end
$upscope $end
$upscope $end
$scope module testcache $end
$scope module mycache $end
$var reg 1 $" \dirty_bit_frm_c[3] $end
$upscope $end
$upscope $end
$enddefinitions $end
$comment Show the parameter values. $end
$dumpall
b11000 U
b100000 T
b100 S
b10 R
b10 Q
b100000 P
b100 O
b10 N
b11 M
b1 L
b0 K
b100000 =
b100000 <
b10 ;
b100000 :
b100 9
b10 8
b11 7
b1 6
b0 5
b100000 -
b10 ,
b100000 +
$end
#0
$dumpvars
x$"
x#"
x""
x!"
bx ~
bx }
bx |
bx {
bx z
bx y
bx x
bx w
xv
xu
xt
xs
xr
xq
xp
xo
bx n
bx m
bx l
bx k
xj
xi
xh
xg
xf
bx e
bx d
bx c
bx b
xa
x`
bx _
bx ^
bx ]
bx \
bx [
bx Z
bx Y
xX
bx W
xV
bx J
b0xxxxxxxxxxxxxxxxxxxxxxxx I
bx H
bx G
bx F
xE
bx D
bx C
bx B
bx A
bx @
bx ?
bx >
bx 4
bx 3
x2
11
x0
x/
bx .
x*
bx )
bx (
x'
bx &
x%
x$
bx #
x"
x!
$end
#1000
0V
0$
0%
0*
b0 [
b0 \
0"
0!
0'
bx ~
bx z
xv
1r
x$"
bx n
xj
bx }
bx y
xu
1q
x#"
bx m
xi
bx |
bx x
xt
1p
x""
bx l
xh
bx {
bx w
xs
1o
x!"
bx k
xg
0X
b0 @
b0 B
b0 e
0f
b0 c
b0 d
0a
b0 b
0`
b100 ^
b100 ]
12
#2000
02
#5000
01
#7000
b1 [
b0 I
0E
b0 _
b0 (
b0 4
b0 Y
b0 ~
b0 z
0v
1r
0$"
b0 n
0j
b0 }
b0 y
0u
1q
0#"
b0 m
0i
b0 |
b0 x
0t
1p
0""
b0 l
0h
b0 {
b0 w
0s
1o
0!"
b0 k
0g
b100 ]
b0 J
b10 G
b0 H
b0 F
00
1/
b1010 .
b1010 C
#10000
b1 @
1%
1*
b1 \
b0 >
11
#15000
01
#17000
b0 ~
b0 z
0v
1r
0$"
b0 n
0j
b0 }
b0 y
0u
1q
0#"
b0 m
0i
b0 |
b0 x
0t
1p
0""
b0 l
0h
b0 {
b0 w
0s
1o
0!"
b0 k
0g
b100 ]
b0 G
b10 .
b10 C
#20000
1'
b1 B
11
#25000
01
#30000
b1 >
b1xxxxxxxxxxxxxxxxxxxxxxxxxxxxxxxxxxxxxxxxxxxxxxxxxxxxxxxxxxxxxxxxxxxxxxxxxxxxxxxxxxxxxxxxxxxxxxxx &
b1xxxxxxxxxxxxxxxxxxxxxxxxxxxxxxxxxxxxxxxxxxxxxxxxxxxxxxxxxxxxxxxxxxxxxxxxxxxxxxxxxxxxxxxxxxxxxxxx A
b1xxxxxxxxxxxxxxxxxxxxxxxxxxxxxxxxxxxxxxxxxxxxxxxxxxxxxxxxxxxxxxxxxxxxxxxxxxxxxxxxxxxxxxxxxxxxxxxx D
11
#35000
01
#40000
b1xxxxxxxxxxxxxxxxxxxxxxxxxxxxxxxxxxxxxxxxxxxxxxxxxxxxxxxxxxxxxxxx &
b1xxxxxxxxxxxxxxxxxxxxxxxxxxxxxxxxxxxxxxxxxxxxxxxxxxxxxxxxxxxxxxxx A
b1xxxxxxxxxxxxxxxxxxxxxxxxxxxxxxxxxxxxxxxxxxxxxxxxxxxxxxxxxxxxxxxx D
b10 >
11
#45000
01
#50000
b11 @
b11 >
b1xxxxxxxxxxxxxxxxxxxxxxxxxxxxxxxx &
b1xxxxxxxxxxxxxxxxxxxxxxxxxxxxxxxx A
b1xxxxxxxxxxxxxxxxxxxxxxxxxxxxxxxx D
11
#55000
01
#60000
0%
b11 [
b0 @
1"
0'
b11 B
b1000000000000000000000000000000000000000000000000000000000000000000000000000000000000000000000001 &
b1000000000000000000000000000000000000000000000000000000000000000000000000000000000000000000000001 A
b1000000000000000000000000000000000000000000000000000000000000000000000000000000000000000000000001 D
b0 >
11
#65000
01
#70000
1V
b0 [
0"
b11 \
b0 B
11
#75000
01
#80000
0V
0*
b0 \
b1 _
b0 ~
b0 z
0v
1r
0$"
b0 n
0j
b0 }
b0 y
0u
1q
0#"
b0 m
0i
b0 |
b0 x
0t
1p
0""
b0 l
0h
b1 )
b1 W
1X
b100 {
b1 w
1s
1o
0!"
b0 k
1g
b100 ]
11
