verilog/modules/cache.v
module cache (
    busywait, data, reset, clk, address
);
    input reset, clk;
    input [line_size - 1:0] address;

    output reg [line_size - 1:0] data;
    output busywait;

    parameter line_size = 32, assiotivity = 1, index_depth = 4, offset_size = 2;
    parameter tag_size = line_size - index_depth - offset_size - 2;
    integer i, j;

    reg [line_size - 1 : 0] word_reg[0 : (2**index_depth) - 1][0 : (2**assiotivity) - 1][0 : (2**offset_size) - 1];
    reg [tag_size - 1 : 0] tag_reg[0 : (2**index_depth) - 1][0 : (2**assiotivity) - 1];
    reg valid_bit_reg [0 : (2**index_depth) - 1][0 : (2**assiotivity) - 1];

    wire [offset_size - 1:0] offset;
    wire [index_depth - 1:0] index;
    wire [tag_size - 1:0] tag;


    reg valid_assiotivity [0 : (2**assiotivity) - 1], hit_tag_assiotivity [0 : (2**assiotivity) - 1], hit_AND_valid [0 : (2**assiotivity) - 1];
    reg [tag_size - 1:0] tag_assiotivity [0 : (2**assiotivity) - 1];
    reg [line_size - 1 : 0] data_cache [0 : (2**assiotivity) - 1];

    reg [assiotivity - 1 : 0] hit_cache_assiotivity;
    reg hit;


    //{tag:}{index:}{offset:}{2}
    assign offset = address[offset_size + 1:2];
    assign index = address[index_depth + offset_size + 1:offset_size + 2];
    assign tag = address[line_size - 1:index_depth + offset_size + 2];


    always @(*) begin
        hit = 1'b0;
        for (i = 0; i < assiotivity; i = i + 1) begin
            valid_assiotivity[i] = valid_bit_reg[index][i];
            tag_assiotivity[i] = tag_reg[index][i];
            hit_tag_assiotivity[i] = (tag === tag_assiotivity[i]) ? 1'b1 : 1'b0;
            hit_AND_valid[i] = valid_assiotivity[i] && hit_tag_assiotivity[i];
            data_cache[i] = word_reg[index][i][offset];

            if (hit_AND_valid[i]) begin
                hit = 1'b1;
                data = data_cache[i]; 
            end
            // else
            // begin
            //     hit = 1'b0;
            // end

        end
    end

    always @(posedge clk, reset)
    begin
        if(reset)
        begin
            for (i = 0; i < 2**index_depth; i = i + 1) begin
                for (j = 0; j < 2**assiotivity; j = j + 1) begin
                    valid_bit_reg[i][j] = 0;
                end
            end
        end
        else
        begin
            //need to integreate
            for (i = 0; i < 2**index_depth; i = i + 1) begin
                for (j = 0; j < 2**assiotivity; j = j + 1) begin
                    valid_bit_reg[9][0] = 0;
                    tag_reg[9][0] = 24'h800001;
                    word_reg[9][0][2] = 32'b11;
                end
            end
        end
    end
    

endmodule

verilog/testbench/cache.v
`timescale 1ns/1ps

`include "../modules/cache.v"


module testcache;

    // input reset, clk;
    // input [line_size - 1:0] address;

    // output reg [line_size - 1:0] data;
    // output busywait;
    parameter line_size = 32;

    wire busywait;
    wire [line_size - 1:0] data;
    reg [line_size - 1:0] address;
    reg clk,reset;
    integer i,j;
    

    cache mycache(busywait, data, reset, clk, address);

	//wavedata file
	initial
	begin
		$dumpfile("wavedata.vcd");
		$dumpvars(0,testcache);
        // $dumpvars(0, mycache.tag_reg[0]);
    
        // for(i = 0; i < 4; i = i + 1)begin
        //     // $dumpvars(0, mycache.valid_bit_reg[1][i]);
        //     $dumpvars(0, mycache.valid_bit_reg[9][i]);
        // end
        $dumpvars(0, mycache.valid_bit_reg[9][0]);
        $dumpvars(0, mycache.valid_bit_reg[9][1]);

        $dumpvars(0, mycache.tag_reg[9][0]);
        $dumpvars(0, mycache.tag_reg[9][1]);

        $dumpvars(0, mycache.word_reg[9][0][2]);
        $dumpvars(0, mycache.word_reg[9][1][2]);
        $dumpvars(0, mycache.word_reg[9][0][3]);
        $dumpvars(0, mycache.word_reg[9][1][3]);

        // $dumpvars(0, mycache.valid_bit_reg[9][0]);
        // $dumpvars(0, mycache.valid_bit_reg[9][1]);

        for(i = 0; i < 2; i = i + 1)begin
            // $dumpvars(0, mycache.valid_bit_reg[1][i]);
            $dumpvars(0, mycache.valid_assiotivity[i]);
            $dumpvars(0, mycache.tag_assiotivity[i]);
            $dumpvars(0, mycache.hit_tag_assiotivity[i]);
            $dumpvars(0, mycache.hit_AND_valid[i]);
            $dumpvars(0, mycache.data_cache[i]);
        end
        
	end

  //clock 
	always 
	begin
			#5	clk = ~clk;
	end

	//running
	initial
	begin
        clk = 1'b1;
        #1
        reset <= 1'b1;

        #1
        reset <= 1'b0;

        #5 
        address <= 32'b100000000000000000000001_1001_10_10;
        
        #10
        address <= 32'd2;

        #10
        reset <= 1'b1;

        #10

        $finish;

	end
		 
endmodule

verilog/testbench/wavedata.vcd
$date
	Sun Dec 31 16:45:28 2023
$end
$version
	Icarus Verilog
$end
$timescale
	1ps
$end
$scope module testcache $end
$var wire 1 ! busywait $end
$var wire 32 " data [31:0] $end
$var parameter 32 # line_size $end
$var reg 32 $ address [31:0] $end
$var reg 1 % clk $end
$var reg 1 & reset $end
$var integer 32 ' i [31:0] $end
$scope module mycache $end
$var wire 32 ( address [31:0] $end
$var wire 1 ! busywait $end
$var wire 1 % clk $end
$var wire 1 & reset $end
$var wire 24 ) tag [23:0] $end
$var wire 2 * offset [1:0] $end
$var wire 4 + index [3:0] $end
$var parameter 32 , assiotivity $end
$var parameter 32 - index_depth $end
$var parameter 32 . line_size $end
$var parameter 32 / offset_size $end
$var parameter 35 0 tag_size $end
$var reg 32 1 data [31:0] $end
$var reg 1 2 hit $end
$var integer 32 3 i [31:0] $end
$var integer 32 4 j [31:0] $end
$upscope $end
$upscope $end
$scope module testcache $end
$scope module mycache $end
$var reg 1 5 \valid_bit_reg[18] $end
$upscope $end
$upscope $end
$scope module testcache $end
$scope module mycache $end
$var reg 1 6 \valid_bit_reg[19] $end
$upscope $end
$upscope $end
$scope module testcache $end
$scope module mycache $end
$var reg 24 7 \tag_reg[18] [23:0] $end
$upscope $end
$upscope $end
$scope module testcache $end
$scope module mycache $end
$var reg 24 8 \tag_reg[19] [23:0] $end
$upscope $end
$upscope $end
$scope module testcache $end
$scope module mycache $end
$var reg 32 9 \word_reg[74] [31:0] $end
$upscope $end
$upscope $end
$scope module testcache $end
$scope module mycache $end
$var reg 32 : \word_reg[78] [31:0] $end
$upscope $end
$upscope $end
$scope module testcache $end
$scope module mycache $end
$var reg 32 ; \word_reg[75] [31:0] $end
$upscope $end
$upscope $end
$scope module testcache $end
$scope module mycache $end
$var reg 32 < \word_reg[79] [31:0] $end
$upscope $end
$upscope $end
$scope module testcache $end
$scope module mycache $end
$var reg 1 = \valid_assiotivity[0] $end
$upscope $end
$upscope $end
$scope module testcache $end
$scope module mycache $end
$var reg 24 > \tag_assiotivity[0] [23:0] $end
$upscope $end
$upscope $end
$scope module testcache $end
$scope module mycache $end
$var reg 1 ? \hit_tag_assiotivity[0] $end
$upscope $end
$upscope $end
$scope module testcache $end
$scope module mycache $end
$var reg 1 @ \hit_AND_valid[0] $end
$upscope $end
$upscope $end
$scope module testcache $end
$scope module mycache $end
$var reg 32 A \data_cache[0] [31:0] $end
$upscope $end
$upscope $end
$scope module testcache $end
$scope module mycache $end
$var reg 1 B \valid_assiotivity[1] $end
$upscope $end
$upscope $end
$scope module testcache $end
$scope module mycache $end
$var reg 24 C \tag_assiotivity[1] [23:0] $end
$upscope $end
$upscope $end
$scope module testcache $end
$scope module mycache $end
$var reg 1 D \hit_tag_assiotivity[1] $end
$upscope $end
$upscope $end
$scope module testcache $end
$scope module mycache $end
$var reg 1 E \hit_AND_valid[1] $end
$upscope $end
$upscope $end
$scope module testcache $end
$scope module mycache $end
$var reg 32 F \data_cache[1] [31:0] $end
$upscope $end
$upscope $end
$enddefinitions $end
$comment Show the parameter values. $end
$dumpall
b11000 0
b10 /
b100000 .
b100 -
b1 ,
b100000 #
$end
#0
$dumpvars
bx F
xE
xD
bx C
xB
bx A
x@
1?
bx >
x=
bx <
bx ;
bx :
b11 9
bx 8
b100000000000000000000001 7
x6
05
b10 4
b1 3
02
bx 1
bx +
bx *
bx )
bx (
b10 '
x&
1%
bx $
bx "
z!
$end
#1000
bx A
x@
1?
bx >
x=
06
05
b10 4
b1 3
1&
#2000
b11 9
b100000000000000000000001 7
05
b10 4
b10000 3
0&
#5000
0%
#7000
b11 A
0@
1?
b100000000000000000000001 >
0=
b1 3
b10 *
b1001 +
b100000000000000000000001 )
b10000000000000000000000110011010 $
b10000000000000000000000110011010 (
#10000
b11 9
b100000000000000000000001 7
05
b10 4
b10000 3
1%
#15000
0%
#17000
bx A
0@
0?
bx >
0=
b1 3
b0 *
b0 +
b0 )
b10 $
b10 (
#20000
b11 9
b100000000000000000000001 7
05
b10 4
b10000 3
1%
#25000
0%
#27000
06
05
b10 4
b10000 3
1&
#30000
06
05
b10 4
b10000 3
1%
